microservice_shared/__init__.py
microservice_shared/create_user_and_db.py
microservice_shared/jwt_utils.py
microservice_shared/logging_config.py
microservice_shared/test_config.py
microservice_shared/test_utils.py
microservice_shared/utils.py
microservice_shared/validation_regex_patterns.py
microservice_shared-0.4.7.dist-info/WHEEL
microservice_shared-0.4.7.dist-info/METADATA
microservice_shared-0.4.7.dist-info/RECORD
