Metadata-Version: 2.1
Name: microservice_shared
Version: 0.4.7
Summary: Microservice Shared Package
Home-page: https://findmyjobz.com
License: MIT
Keywords: job search
Author: Manikandan
Author-email: manikandan.findmyjobz@gmail.com
Classifier: Development Status :: 3 - Alpha
Classifier: Intended Audience :: Developers
Classifier: License :: OSI Approved :: MIT License
Classifier: Programming Language :: Python :: 3.11
